{
  "name": "Firemerge Release Watcher",
  "nodes": [
    {
      "parameters": {
        "rule": {
          "interval": [
            {
              "triggerAtHour": 23
            }
          ]
        }
      },
      "id": "400f43d5-9ee8-4b0f-9efa-b7c0a7ebf469",
      "name": "Daily Check",
      "type": "n8n-nodes-base.scheduleTrigger",
      "typeVersion": 1.2,
      "position": [-1024, 928]
    },
    {
      "parameters": {
        "url": "https://api.github.com/repos/lvu/firemerge/tags",
        "options": {}
      },
      "id": "0c017bb2-8877-4ed7-b8a7-824db324cf34",
      "name": "Get GitHub Tags",
      "type": "n8n-nodes-base.httpRequest",
      "typeVersion": 4.2,
      "position": [-816, 928]
    },
    {
      "parameters": {
        "url": "https://api.github.com/repos/anthony-spruyt/container-images/releases",
        "options": {
          "response": {
            "response": {}
          }
        }
      },
      "id": "d3c408ae-87f6-4d55-8c7d-c3f2aa4b33b3",
      "name": "Get GitHub Releases",
      "type": "n8n-nodes-base.httpRequest",
      "typeVersion": 4.2,
      "position": [-592, 928]
    },
    {
      "parameters": {
        "jsCode": "// Get the latest tag from the upstream GitHub API response\n// Access tags from earlier node since releases are now the input\nconst tags = $('Get GitHub Tags').all();\nif (!tags || tags.length === 0 || !tags[0].json) {\n  return [{ json: { isNew: false, version: null, error: 'No tags found' } }];\n}\n\n// First item is the latest tag (GitHub returns tags sorted by creation date desc)\nconst latestTag = tags[0].json;\nif (!latestTag.name) {\n  return [{ json: { isNew: false, version: null, error: 'Invalid tag data' } }];\n}\n\n// Keep version as-is from upstream tag (needed for git checkout)\nconst version = latestTag.name;\n\n// Check GitHub releases to see if this version was already built\n// Release tag format: firemerge-{version} or firemerge-{version}-rN (for retries)\n// Get ALL releases from input (n8n splits array responses into multiple items)\nconst releases = $input.all().map(item => item.json);\nconst releasePattern = new RegExp(`^firemerge-${version.replace(/[.*+?^${}()|[\\]\\\\]/g, '\\\\$&')}(-r[0-9]+)?$`);\nconst existingRelease = releases.find(r => releasePattern.test(r.tag_name));\n\nconst isNew = !existingRelease;\n\nreturn [{\n  json: {\n    isNew: isNew,\n    version: version,\n    existingRelease: existingRelease ? existingRelease.tag_name : null,\n    commitSha: latestTag.commit?.sha || null\n  }\n}];"
      },
      "id": "dc8b92f9-de80-4e57-89f8-3b7cf13b9080",
      "name": "Check New Version",
      "type": "n8n-nodes-base.code",
      "typeVersion": 2,
      "position": [-368, 928]
    },
    {
      "parameters": {
        "conditions": {
          "options": {
            "caseSensitive": true,
            "leftValue": "",
            "typeValidation": "strict"
          },
          "conditions": [
            {
              "id": "condition-new-version",
              "leftValue": "={{ $json.isNew }}",
              "rightValue": true,
              "operator": {
                "type": "boolean",
                "operation": "equals"
              }
            }
          ],
          "combinator": "and"
        },
        "options": {}
      },
      "id": "379fb109-8d9e-4e1f-8aeb-a17b0e1b7371",
      "name": "Is New Version?",
      "type": "n8n-nodes-base.if",
      "typeVersion": 2,
      "position": [-144, 928]
    },
    {
      "parameters": {
        "jsCode": "// Update static data with the new version (kept for backwards compatibility)\nconst staticData = $getWorkflowStaticData('global');\nconst version = $('Check New Version').item.json.version;\nstaticData.lastVersion_firemerge = version;\n\nreturn [{\n  json: {\n    success: true,\n    version: version,\n    message: `Updated last version to ${version}`\n  }\n}];"
      },
      "id": "e4d44d9f-f4e3-4ded-b104-78b0b718a5d9",
      "name": "Update State",
      "type": "n8n-nodes-base.code",
      "typeVersion": 2,
      "position": [80, 816]
    },
    {
      "parameters": {
        "method": "POST",
        "url": "https://api.github.com/repos/anthony-spruyt/container-images/actions/workflows/build-and-push.yaml/dispatches",
        "authentication": "genericCredentialType",
        "genericAuthType": "httpHeaderAuth",
        "sendHeaders": true,
        "headerParameters": {
          "parameters": [
            {
              "name": "Accept",
              "value": "application/vnd.github.v3+json"
            }
          ]
        },
        "sendBody": true,
        "specifyBody": "json",
        "jsonBody": "={\n  \"ref\": \"main\",\n  \"inputs\": {\n    \"image\": \"firemerge\",\n    \"version\": \"{{ $('Check New Version').item.json.version }}\",\n    \"dry_run\": \"false\"\n  }\n}",
        "options": {}
      },
      "id": "25bba67c-0125-4bc0-b253-4977c925ef55",
      "name": "Trigger Build Workflow",
      "type": "n8n-nodes-base.httpRequest",
      "typeVersion": 4.2,
      "position": [304, 816],
      "credentials": {
        "httpHeaderAuth": {
          "id": "CONFIGURE_ME",
          "name": "GitHub PAT"
        }
      }
    },
    {
      "parameters": {
        "fromEmail": "noreply@example.com",
        "toEmail": "CONFIGURE_ME@example.com",
        "subject": "=Firemerge {{ $('Check New Version').item.json.version }} - Build triggered",
        "options": {}
      },
      "id": "019dd2b6-cc59-4a92-88ff-f3870a0088ac",
      "name": "Send Notification",
      "type": "n8n-nodes-base.emailSend",
      "typeVersion": 2.1,
      "position": [512, 816],
      "credentials": {
        "smtp": {
          "id": "CONFIGURE_ME",
          "name": "SMTP"
        }
      }
    }
  ],
  "pinData": {},
  "connections": {
    "Daily Check": {
      "main": [
        [
          {
            "node": "Get GitHub Tags",
            "type": "main",
            "index": 0
          }
        ]
      ]
    },
    "Get GitHub Tags": {
      "main": [
        [
          {
            "node": "Get GitHub Releases",
            "type": "main",
            "index": 0
          }
        ]
      ]
    },
    "Get GitHub Releases": {
      "main": [
        [
          {
            "node": "Check New Version",
            "type": "main",
            "index": 0
          }
        ]
      ]
    },
    "Check New Version": {
      "main": [
        [
          {
            "node": "Is New Version?",
            "type": "main",
            "index": 0
          }
        ]
      ]
    },
    "Is New Version?": {
      "main": [
        [
          {
            "node": "Update State",
            "type": "main",
            "index": 0
          }
        ]
      ]
    },
    "Update State": {
      "main": [
        [
          {
            "node": "Trigger Build Workflow",
            "type": "main",
            "index": 0
          }
        ]
      ]
    },
    "Trigger Build Workflow": {
      "main": [
        [
          {
            "node": "Send Notification",
            "type": "main",
            "index": 0
          }
        ]
      ]
    }
  },
  "meta": {
    "templateCredsSetupCompleted": false
  }
}
